[{"kode": "MERK", "nama": "PT Merck Tbk", "sektor": "Healthcare", "harga": 3860.0, "market_cap": 1729279950848.0, "fair_value": 5795.52, "upside_pct": 50.1, "score_fundamental": 99.4, "score_technical": 80.0, "score_news": null, "score_sentiment": null, "score_valuation": 79.2, "score_risk": 72.3, "total_score": 89.2, "rating": "WATCHLIST", "rating_reasons": ["Likuiditas di bawah ambang 1 M IDR/hari"], "confidence": "High", "liquid": false, "daily_value_avg": 90729300, "foreign_net": null, "support": 3450.0, "resistance": 3860.0, "take_profit_1": 3860.0, "take_profit_2": 4179.404146, "take_profit_3": 5795.52, "stop_loss": 3450.0, "risk_reward": 0.0, "rsi": 64.377229, "change_3m": 0.138656, "dividend_yield": 0.0716, "earnings_growth": 3.94, "rank": 1}, {"kode": "SRTG", "nama": "PT Saratoga Investama Sedaya Tbk", "sektor": "Financial Services", "harga": 1675.0, "market_cap": 22695970340864.0, "fair_value": 11534.63, "upside_pct": 588.6, "score_fundamental": 99.9, "score_technical": 68.0, "score_news": null, "score_sentiment": null, "score_valuation": 100.0, "score_risk": 55.9, "total_score": 85.2, "rating": "WATCHLIST", "rating_reasons": ["Technical 68.0 < 75"], "confidence": "Medium", "liquid": true, "daily_value_avg": 3811856125, "foreign_net": null, "support": 1430.0, "resistance": 1690.0, "take_profit_1": 1690.0, "take_profit_2": 1766.628859, "take_profit_3": 11534.63, "stop_loss": 1430.0, "risk_reward": 0.06, "rsi": 66.008776, "change_3m": -0.009844, "dividend_yield": 0.0613, "earnings_growth": null, "rank": 3}, {"kode": "TINS", "nama": "PT TIMAH Tbk", "sektor": "Basic Materials", "harga": 3550.0, "market_cap": 26439522975744.0, "fair_value": 3137.05, "upside_pct": -11.6, "score_fundamental": 94.8, "score_technical": 72.0, "score_news": null, "score_sentiment": null, "score_valuation": 31.7, "score_risk": 51.0, "total_score": 79.6, "rating": "WATCHLIST", "rating_reasons": ["Technical 72.0 < 75", "Total 79.6 < 80"], "confidence": "High", "liquid": true, "daily_value_avg": 101924902000, "foreign_net": null, "support": 3220.0, "resistance": 3780.0, "take_profit_1": 3780.0, "take_profit_2": 4090.401173, "take_profit_3": null, "stop_loss": 3220.0, "risk_reward": 0.7, "rsi": 55.597274, "change_3m": -0.05301, "dividend_yield": 0.024700000000000003, "earnings_growth": 11.842, "rank": 6}, {"kode": "NICK", "nama": "PT Charnic Capital Tbk", "sektor": "Real Estate", "harga": 1075.0, "market_cap": 699986280448.0, "fair_value": 3226.04, "upside_pct": 200.1, "score_fundamental": 100.0, "score_technical": 58.9, "score_news": null, "score_sentiment": null, "score_valuation": 68.8, "score_risk": 36.8, "total_score": 78.7, "rating": "WATCHLIST", "rating_reasons": ["Technical 58.9 < 75", "Total 78.7 < 80", "Likuiditas di bawah ambang 1 M IDR/hari"], "confidence": "Medium", "liquid": false, "daily_value_avg": 10008250, "foreign_net": null, "support": 955.0, "resistance": 1120.0, "take_profit_1": 1120.0, "take_profit_2": 1390.0, "take_profit_3": 3226.04, "stop_loss": 955.0, "risk_reward": 0.38, "rsi": 59.310671, "change_3m": -0.185606, "dividend_yield": null, "earnings_growth": null, "rank": 7}, {"kode": "BSSR", "nama": "PT Baramulti Suksessarana Tbk", "sektor": "Energy", "harga": 4270.0, "market_cap": 11172454596608.0, "fair_value": 4552.93, "upside_pct": 6.6, "score_fundamental": 83.2, "score_technical": 76.8, "score_news": null, "score_sentiment": null, "score_valuation": 47.6, "score_risk": 82.1, "total_score": 78.5, "rating": "WATCHLIST", "rating_reasons": ["Total 78.5 < 80"], "confidence": "Medium", "liquid": true, "daily_value_avg": 5766165300, "foreign_net": null, "support": 3930.0, "resistance": 4340.0, "take_profit_1": 4340.0, "take_profit_2": 4340.0, "take_profit_3": 4552.93, "stop_loss": 3930.0, "risk_reward": 0.21, "rsi": 78.144985, "change_3m": 0.190833, "dividend_yield": 0.19579999999999997, "earnings_growth": 0.305, "rank": 8}, {"kode": "YULE", "nama": "PT Yulie Sekuritas Indonesia Tbk", "sektor": "Financial Services", "harga": 3350.0, "market_cap": 5317410684928.0, "fair_value": 765.32, "upside_pct": -77.2, "score_fundamental": 84.7, "score_technical": 81.7, "score_news": null, "score_sentiment": null, "score_valuation": 0.0, "score_risk": 75.6, "total_score": 77.7, "rating": "WATCHLIST", "rating_reasons": ["Total 77.7 < 80", "Likuiditas di bawah ambang 1 M IDR/hari"], "confidence": "Medium", "liquid": false, "daily_value_avg": 34672500, "foreign_net": null, "support": 3010.0, "resistance": 3540.0, "take_profit_1": 3540.0, "take_profit_2": 4180.0, "take_profit_3": null, "stop_loss": 3010.0, "risk_reward": 0.56, "rsi": 51.288386, "change_3m": -0.002976, "dividend_yield": 0.3, "earnings_growth": null, "rank": 9}, {"kode": "PSAB", "nama": "PT J Resources Asia Pasifik Tbk", "sektor": "Basic Materials", "harga": 418.0, "market_cap": 11060280033280.0, "fair_value": 1113.64, "upside_pct": 166.4, "score_fundamental": 89.8, "score_technical": 64.5, "score_news": null, "score_sentiment": null, "score_valuation": 68.8, "score_risk": 47.1, "total_score": 76.3, "rating": "WATCHLIST", "rating_reasons": ["Technical 64.5 < 75", "Total 76.3 < 80"], "confidence": "High", "liquid": true, "daily_value_avg": 33609231480, "foreign_net": null, "support": 374.0, "resistance": 448.0, "take_profit_1": 448.0, "take_profit_2": 494.0, "take_profit_3": 1113.64, "stop_loss": 374.0, "risk_reward": 0.68, "rsi": 52.514814, "change_3m": -0.085612, "dividend_yield": 0.2465, "earnings_growth": 22.264, "rank": 10}, {"kode": "ADES", "nama": "PT Akasha Wira International Tbk", "sektor": "Consumer Defensive", "harga": 33250.0, "market_cap": 19614069161984.0, "fair_value": 12907.8, "upside_pct": -61.2, "score_fundamental": 90.7, "score_technical": 69.8, "score_news": null, "score_sentiment": null, "score_valuation": 0.0, "score_risk": 68.8, "total_score": 75.8, "rating": "WATCHLIST", "rating_reasons": ["Technical 69.8 < 75", "Total 75.8 < 80"], "confidence": "Medium", "liquid": true, "daily_value_avg": 2949275000, "foreign_net": null, "support": 26700.0, "resistance": 37200.0, "take_profit_1": 37200.0, "take_profit_2": 37200.0, "take_profit_3": null, "stop_loss": 26700.0, "risk_reward": 0.6, "rsi": 61.590685, "change_3m": 1.027439, "dividend_yield": null, "earnings_growth": 0.748, "rank": 11}, {"kode": "PBID", "nama": "PT Panca Budi Idaman Tbk", "sektor": "Consumer Cyclical", "harga": 484.0, "market_cap": 3630000242688.0, "fair_value": 919.12, "upside_pct": 89.9, "score_fundamental": 71.8, "score_technical": 75.0, "score_news": null, "score_sentiment": null, "score_valuation": 92.7, "score_risk": 80.0, "total_score": 74.8, "rating": "WATCHLIST", "rating_reasons": ["Fundamental 71.8 < 75", "Total 74.8 < 80", "Likuiditas di bawah ambang 1 M IDR/hari"], "confidence": "High", "liquid": false, "daily_value_avg": 209467940, "foreign_net": null, "support": 464.0, "resistance": 488.0, "take_profit_1": 488.0, "take_profit_2": 506.522554, "take_profit_3": 919.12, "stop_loss": 464.0, "risk_reward": 0.2, "rsi": 57.961171, "change_3m": 0.029038, "dividend_yield": 0.11, "earnings_growth": 0.239, "rank": 12}, {"kode": "MDIY", "nama": null, "sektor": "Consumer Cyclical", "harga": 1010.0, "market_cap": 25442295742464.0, "fair_value": 644.18, "upside_pct": -36.2, "score_fundamental": 87.3, "score_technical": 72.7, "score_news": null, "score_sentiment": null, "score_valuation": 23.5, "score_risk": 36.6, "total_score": 74.7, "rating": "WATCHLIST", "rating_reasons": ["Technical 72.7 < 75", "Total 74.7 < 80", "Likuiditas di bawah ambang 1 M IDR/hari"], "confidence": "High", "liquid": false, "daily_value_avg": 507328050, "foreign_net": null, "support": 827.483652, "resistance": 1025.0, "take_profit_1": 1025.0, "take_profit_2": 1025.0, "take_profit_3": null, "stop_loss": 827.483652, "risk_reward": 0.08, "rsi": 75.665974, "change_3m": 0.158854, "dividend_yield": 0.0351, "earnings_growth": 0.358, "rank": 13}, {"kode": "AMOR", "nama": "PT Ashmore Asset Management Indonesia Tbk", "sektor": "Financial Services", "harga": 344.0, "market_cap": 754991955968.0, "fair_value": 286.04, "upside_pct": -16.8, "score_fundamental": 91.2, "score_technical": 61.1, "score_news": null, "score_sentiment": null, "score_valuation": 31.0, "score_risk": 62.6, "total_score": 74.4, "rating": "WATCHLIST", "rating_reasons": ["Technical 61.1 < 75", "Total 74.4 < 80", "Likuiditas di bawah ambang 1 M IDR/hari"], "confidence": "High", "liquid": false, "daily_value_avg": 72740520, "foreign_net": null, "support": 300.0, "resistance": 348.0, "take_profit_1": 348.0, "take_profit_2": 370.0, "take_profit_3": null, "stop_loss": 300.0, "risk_reward": 0.09, "rsi": 64.769911, "change_3m": -0.07027, "dividend_yield": 0.0916, "earnings_growth": 0.24, "rank": 14}, {"kode": "SMSM", "nama": "PT Selamat Sempurna Tbk", "sektor": "Consumer Cyclical", "harga": 1755.0, "market_cap": 10106475380736.0, "fair_value": 2605.64, "upside_pct": 48.5, "score_fundamental": 77.8, "score_technical": 70.0, "score_news": null, "score_sentiment": null, "score_valuation": 66.9, "score_risk": 76.0, "total_score": 74.1, "rating": "WATCHLIST", "rating_reasons": ["Technical 70.0 < 75", "Total 74.1 < 80"], "confidence": "High", "liquid": true, "daily_value_avg": 2278068975, "foreign_net": null, "support": 1585.0, "resistance": 1755.0, "take_profit_1": 1755.0, "take_profit_2": 1870.0, "take_profit_3": 2605.64, "stop_loss": 1585.0, "risk_reward": 0.0, "rsi": 69.321083, "change_3m": -0.000427, "dividend_yield": 0.0802, "earnings_growth": -0.063, "rank": 15}, {"kode": "WINS", "nama": "PT Wintermar Offshore Marine Tbk", "sektor": "Industrials", "harga": 540.0, "market_cap": 2413684064256.0, "fair_value": 459.07, "upside_pct": -15.0, "score_fundamental": 79.6, "score_technical": 74.8, "score_news": null, "score_sentiment": null, "score_valuation": 35.0, "score_risk": 64.3, "total_score": 74.1, "rating": "WATCHLIST", "rating_reasons": ["Technical 74.8 < 75", "Total 74.1 < 80", "Likuiditas di bawah ambang 1 M IDR/hari"], "confidence": "High", "liquid": false, "daily_value_avg": 840464100, "foreign_net": null, "support": 500.0, "resistance": 550.0, "take_profit_1": 550.0, "take_profit_2": 569.755798, "take_profit_3": null, "stop_loss": 500.0, "risk_reward": 0.25, "rsi": 59.024624, "change_3m": 0.077861, "dividend_yield": 0.0166, "earnings_growth": 1.956, "rank": 16}, {"kode": "EAST", "nama": "PT Eastparc Hotel Tbk", "sektor": "Consumer Cyclical", "harga": 90.0, "market_cap": 371376488448.0, "fair_value": 128.29, "upside_pct": 42.5, "score_fundamental": 71.0, "score_technical": 76.0, "score_news": null, "score_sentiment": null, "score_valuation": 78.3, "score_risk": 74.5, "total_score": 73.5, "rating": "WATCHLIST", "rating_reasons": ["Fundamental 71.0 < 75", "Total 73.5 < 80", "Likuiditas di bawah ambang 1 M IDR/hari"], "confidence": "High", "liquid": false, "daily_value_avg": 73418400, "foreign_net": null, "support": 85.0, "resistance": 91.0, "take_profit_1": 91.0, "take_profit_2": 91.118281, "take_profit_3": 128.29, "stop_loss": 85.0, "risk_reward": 0.2, "rsi": 60.466232, "change_3m": -0.001765, "dividend_yield": 0.10439999999999999, "earnings_growth": 0.607, "rank": 17}, {"kode": "WIIM", "nama": "PT Wismilak Inti Makmur Tbk", "sektor": "Consumer Defensive", "harga": 1585.0, "market_cap": 3307742429184.0, "fair_value": 2306.87, "upside_pct": 45.5, "score_fundamental": 89.0, "score_technical": 55.0, "score_news": null, "score_sentiment": null, "score_valuation": 83.8, "score_risk": 40.8, "total_score": 72.9, "rating": "WATCHLIST", "rating_reasons": ["Technical 55.0 < 75", "Total 72.9 < 80"], "confidence": "High", "liquid": true, "daily_value_avg": 1098119700, "foreign_net": null, "support": 1500.0, "resistance": 1700.0, "take_profit_1": 1700.0, "take_profit_2": 1918.990949, "take_profit_3": 2306.87, "stop_loss": 1500.0, "risk_reward": 1.35, "rsi": 49.691773, "change_3m": -0.089217, "dividend_yield": 0.0655, "earnings_growth": 1.014, "rank": 18}, {"kode": "LPGI", "nama": "PT Lippo General Insurance Tbk", "sektor": "Financial Services", "harga": 690.0, "market_cap": 2070000041984.0, "fair_value": 473.4, "upside_pct": -31.4, "score_fundamental": 76.0, "score_technical": 82.5, "score_news": null, "score_sentiment": null, "score_valuation": 22.2, "score_risk": 37.6, "total_score": 72.7, "rating": "WATCHLIST", "rating_reasons": ["Total 72.7 < 80", "Likuiditas di bawah ambang 1 M IDR/hari"], "confidence": "Medium", "liquid": false, "daily_value_avg": 6586050, "foreign_net": null, "support": 615.0, "resistance": 700.0, "take_profit_1": 700.0, "take_profit_2": 768.695686, "take_profit_3": null, "stop_loss": 615.0, "risk_reward": 0.13, "rsi": 56.630896, "change_3m": 0.014706, "dividend_yield": 0.0149, "earnings_growth": null, "rank": 19}, {"kode": "MLBI", "nama": "PT Multi Bintang Indonesia Tbk", "sektor": "Consumer Defensive", "harga": 6325.0, "market_cap": 13326774960128.0, "fair_value": 3991.93, "upside_pct": -36.9, "score_fundamental": 84.1, "score_technical": 62.5, "score_news": null, "score_sentiment": null, "score_valuation": 24.9, "score_risk": 77.8, "total_score": 71.9, "rating": "WATCHLIST", "rating_reasons": ["Technical 62.5 < 75", "Total 71.9 < 80", "Likuiditas di bawah ambang 1 M IDR/hari"], "confidence": "High", "liquid": false, "daily_value_avg": 735850500, "foreign_net": null, "support": 5879.0, "resistance": 6450.0, "take_profit_1": 6450.0, "take_profit_2": 6450.0, "take_profit_3": null, "stop_loss": 5879.0, "risk_reward": 0.28, "rsi": 67.565215, "change_3m": 0.174523, "dividend_yield": 0.08869999999999999, "earnings_growth": 0.175, "rank": 20}, {"kode": "DKFT", "nama": "PT Central Omega Resources Tbk", "sektor": "Basic Materials", "harga": 665.0, "market_cap": 3666468143104.0, "fair_value": 904.43, "upside_pct": 36.0, "score_fundamental": 95.3, "score_technical": 46.8, "score_news": null, "score_sentiment": null, "score_valuation": 67.8, "score_risk": 38.6, "total_score": 71.8, "rating": "WATCHLIST", "rating_reasons": ["Technical 46.8 < 75", "Total 71.8 < 80"], "confidence": "High", "liquid": true, "daily_value_avg": 2058720300, "foreign_net": null, "support": 590.0, "resistance": 715.0, "take_profit_1": 715.0, "take_profit_2": 850.0, "take_profit_3": 904.43, "stop_loss": 590.0, "risk_reward": 0.67, "rsi": 53.018898, "change_3m": -0.125, "dividend_yield": 0.10369999999999999, "earnings_growth": 0.73, "rank": 21}, {"kode": "CBPE", "nama": "PT Citra Buana Prasida Tbk", "sektor": "Real Estate", "harga": 284.0, "market_cap": 385174994944.0, "fair_value": 214.3, "upside_pct": -24.5, "score_fundamental": 95.7, "score_technical": 54.0, "score_news": null, "score_sentiment": null, "score_valuation": 18.3, "score_risk": 38.9, "total_score": 71.7, "rating": "WATCHLIST", "rating_reasons": ["Technical 54.0 < 75", "Total 71.7 < 80", "Likuiditas di bawah ambang 1 M IDR/hari"], "confidence": "Medium", "liquid": false, "daily_value_avg": 113005020, "foreign_net": null, "support": 233.145985, "resistance": 312.854004, "take_profit_1": 312.854004, "take_profit_2": 322.817522, "take_profit_3": null, "stop_loss": 233.145985, "risk_reward": 0.57, "rsi": 51.157926, "change_3m": -0.103647, "dividend_yield": 0.35, "earnings_growth": 1.729, "rank": 22}, {"kode": "KETR", "nama": "PT Ketrosden Triasmitra", "sektor": "Technology", "harga": 540.0, "market_cap": 1534281908224.0, "fair_value": 721.25, "upside_pct": 33.6, "score_fundamental": 83.9, "score_technical": 61.8, "score_news": null, "score_sentiment": null, "score_valuation": 77.6, "score_risk": 28.0, "total_score": 71.7, "rating": "WATCHLIST", "rating_reasons": ["Technical 61.8 < 75", "Total 71.7 < 80"], "confidence": "High", "liquid": true, "daily_value_avg": 7972589700, "foreign_net": null, "support": 462.0, "resistance": 575.0, "take_profit_1": 575.0, "take_profit_2": 680.0, "take_profit_3": 721.25, "stop_loss": 462.0, "risk_reward": 0.45, "rsi": 53.134672, "change_3m": 0.210762, "dividend_yield": null, "earnings_growth": 1.707, "rank": 23}, {"kode": "AUTO", "nama": "PT Astra Otoparts Tbk", "sektor": "Consumer Cyclical", "harga": 2620.0, "market_cap": 12627700875264.0, "fair_value": 7564.52, "upside_pct": 188.7, "score_fundamental": 66.3, "score_technical": 73.7, "score_news": null, "score_sentiment": null, "score_valuation": 99.3, "score_risk": 72.1, "total_score": 71.5, "rating": "WATCHLIST", "rating_reasons": ["Fundamental 66.3 < 75", "Technical 73.7 < 75", "Total 71.5 < 80"], "confidence": "High", "liquid": true, "daily_value_avg": 3107830900, "foreign_net": null, "support": 2320.0, "resistance": 2700.0, "take_profit_1": 2700.0, "take_profit_2": 2700.0, "take_profit_3": 7564.52, "stop_loss": 2320.0, "risk_reward": 0.27, "rsi": 67.146792, "change_3m": 0.022943, "dividend_yield": 0.0867, "earnings_growth": 0.106, "rank": 24}, {"kode": "MAHA", "nama": "PT Mandiri Herindo Adiperkasa Tbk", "sektor": "Industrials", "harga": 141.0, "market_cap": 2311690911744.0, "fair_value": 182.14, "upside_pct": 29.2, "score_fundamental": 74.5, "score_technical": 70.9, "score_news": null, "score_sentiment": null, "score_valuation": 74.7, "score_risk": 48.7, "total_score": 71.5, "rating": "WATCHLIST", "rating_reasons": ["Fundamental 74.5 < 75", "Technical 70.9 < 75", "Total 71.5 < 80", "Likuiditas di bawah ambang 1 M IDR/hari"], "confidence": "High", "liquid": false, "daily_value_avg": 269013900, "foreign_net": null, "support": 128.0, "resistance": 142.0, "take_profit_1": 142.0, "take_profit_2": 145.750005, "take_profit_3": 182.14, "stop_loss": 128.0, "risk_reward": 0.08, "rsi": 64.64019, "change_3m": 0.025455, "dividend_yield": 0.0851, "earnings_growth": 6.886, "rank": 25}, {"kode": "PTSP", "nama": "PT Pioneerindo Gourmet International Tbk", "sektor": "Consumer Cyclical", "harga": 895.0, "market_cap": 197623152640.0, "fair_value": 2403.31, "upside_pct": 168.5, "score_fundamental": 72.4, "score_technical": 72.9, "score_news": null, "score_sentiment": null, "score_valuation": 94.8, "score_risk": 30.0, "total_score": 71.3, "rating": "WATCHLIST", "rating_reasons": ["Fundamental 72.4 < 75", "Technical 72.9 < 75", "Total 71.3 < 80", "Likuiditas di bawah ambang 1 M IDR/hari"], "confidence": "High", "liquid": false, "daily_value_avg": 8466700, "foreign_net": null, "support": 835.0, "resistance": 940.0, "take_profit_1": 940.0, "take_profit_2": 1175.0, "take_profit_3": 2403.31, "stop_loss": 835.0, "risk_reward": 0.75, "rsi": 53.885646, "change_3m": 0.0, "dividend_yield": null, "earnings_growth": 25.005, "rank": 26}, {"kode": "BJTM", "nama": "PT Bank Pembangunan Daerah Jawa Timur Tbk", "sektor": "Financial Services", "harga": 520.0, "market_cap": 7808058654720.0, "fair_value": 1137.94, "upside_pct": 118.8, "score_fundamental": 64.2, "score_technical": 75.0, "score_news": null, "score_sentiment": null, "score_valuation": 95.1, "score_risk": 80.9, "total_score": 71.2, "rating": "WATCHLIST", "rating_reasons": ["Fundamental 64.2 < 75", "Total 71.2 < 80"], "confidence": "Medium", "liquid": true, "daily_value_avg": 2717496600, "foreign_net": null, "support": 500.0, "resistance": 520.0, "take_profit_1": 520.0, "take_profit_2": 545.939514, "take_profit_3": 1137.94, "stop_loss": 500.0, "risk_reward": 0.0, "rsi": 57.523088, "change_3m": -0.023298, "dividend_yield": 0.1099, "earnings_growth": 0.302, "rank": 27}, {"kode": "IPCC", "nama": "PT Indonesia Kendaraan Terminal Tbk", "sektor": "Industrials", "harga": 1230.0, "market_cap": 2236613394432.0, "fair_value": 1257.46, "upside_pct": 2.2, "score_fundamental": 75.9, "score_technical": 69.3, "score_news": null, "score_sentiment": null, "score_valuation": 50.9, "score_risk": 66.0, "total_score": 71.2, "rating": "WATCHLIST", "rating_reasons": ["Technical 69.3 < 75", "Total 71.2 < 80", "Likuiditas di bawah ambang 1 M IDR/hari"], "confidence": "High", "liquid": false, "daily_value_avg": 753233550, "foreign_net": null, "support": 1085.0, "resistance": 1250.0, "take_profit_1": 1250.0, "take_profit_2": 1270.334353, "take_profit_3": 1257.46, "stop_loss": 1085.0, "risk_reward": 0.14, "rsi": 62.69615, "change_3m": 0.016661, "dividend_yield": 0.091, "earnings_growth": 0.032, "rank": 28}, {"kode": "MAPA", "nama": "PT Map Aktif Adiperkasa Tbk", "sektor": "Consumer Cyclical", "harga": 610.0, "market_cap": 17387440046080.0, "fair_value": 943.32, "upside_pct": 54.6, "score_fundamental": 83.7, "score_technical": 55.5, "score_news": null, "score_sentiment": null, "score_valuation": 76.0, "score_risk": 60.5, "total_score": 71.2, "rating": "WATCHLIST", "rating_reasons": ["Technical 55.5 < 75", "Total 71.2 < 80"], "confidence": "High", "liquid": true, "daily_value_avg": 14370428800, "foreign_net": null, "support": 575.0, "resistance": 645.772385, "take_profit_1": 645.772385, "take_profit_2": 675.577216, "take_profit_3": 943.32, "stop_loss": 575.0, "risk_reward": 1.02, "rsi": 52.340575, "change_3m": -0.069707, "dividend_yield": 0.66, "earnings_growth": 0.384, "rank": 29}, {"kode": "MKPI", "nama": "PT Metropolitan Kentjana Tbk", "sektor": "Real Estate", "harga": 21375.0, "market_cap": 20267646582784.0, "fair_value": 14880.81, "upside_pct": -30.4, "score_fundamental": 84.6, "score_technical": 60.2, "score_news": null, "score_sentiment": null, "score_valuation": 24.7, "score_risk": 75.7, "total_score": 71.2, "rating": "WATCHLIST", "rating_reasons": ["Technical 60.2 < 75", "Total 71.2 < 80", "Likuiditas di bawah ambang 1 M IDR/hari"], "confidence": "High", "liquid": false, "daily_value_avg": 967860000, "foreign_net": null, "support": 20100.0, "resistance": 21675.0, "take_profit_1": 21675.0, "take_profit_2": 21960.101754, "take_profit_3": null, "stop_loss": 20100.0, "risk_reward": 0.24, "rsi": 61.061237, "change_3m": -0.027703, "dividend_yield": 0.0444, "earnings_growth": 0.176, "rank": 30}, {"kode": "ADRO", "nama": "PT Alamtri Resources Indonesia Tbk", "sektor": "Energy", "harga": 2510.0, "market_cap": 72289240481792.0, "fair_value": 2299.27, "upside_pct": -8.4, "score_fundamental": 73.2, "score_technical": 71.1, "score_news": null, "score_sentiment": null, "score_valuation": 37.2, "score_risk": 86.1, "total_score": 71.0, "rating": "WATCHLIST", "rating_reasons": ["Fundamental 73.2 < 75", "Technical 71.1 < 75", "Total 71.0 < 80"], "confidence": "High", "liquid": true, "daily_value_avg": 62326575550, "foreign_net": null, "support": 2220.0, "resistance": 2520.0, "take_profit_1": 2520.0, "take_profit_2": 2600.0, "take_profit_3": null, "stop_loss": 2220.0, "risk_reward": 0.03, "rsi": 67.465965, "change_3m": 0.049445, "dividend_yield": 0.0942, "earnings_growth": 0.748, "rank": 31}, {"kode": "LSIP", "nama": "PT Perusahaan Perkebunan London Sumatra Indonesia Tbk", "sektor": "Consumer Defensive", "harga": 1320.0, "market_cap": 9002352115712.0, "fair_value": 3353.83, "upside_pct": 154.1, "score_fundamental": 69.8, "score_technical": 69.6, "score_news": null, "score_sentiment": null, "score_valuation": 100.0, "score_risk": 60.4, "total_score": 71.0, "rating": "WATCHLIST", "rating_reasons": ["Fundamental 69.8 < 75", "Technical 69.6 < 75", "Total 71.0 < 80"], "confidence": "High", "liquid": true, "daily_value_avg": 8997562200, "foreign_net": null, "support": 1162.616565, "resistance": 1350.0, "take_profit_1": 1350.0, "take_profit_2": 1697.045078, "take_profit_3": 3353.83, "stop_loss": 1162.616565, "risk_reward": 0.19, "rsi": 62.711343, "change_3m": -0.120088, "dividend_yield": 0.0622, "earnings_growth": 0.007, "rank": 32}, {"kode": "JRPT", "nama": "PT Jaya Real Property, Tbk.", "sektor": "Real Estate", "harga": 1080.0, "market_cap": 13855708151808.0, "fair_value": 1319.34, "upside_pct": 22.2, "score_fundamental": 73.5, "score_technical": 67.5, "score_news": null, "score_sentiment": null, "score_valuation": 60.3, "score_risk": 80.1, "total_score": 70.8, "rating": "WATCHLIST", "rating_reasons": ["Fundamental 73.5 < 75", "Technical 67.5 < 75", "Total 70.8 < 80", "Likuiditas di bawah ambang 1 M IDR/hari"], "confidence": "High", "liquid": false, "daily_value_avg": 808633800, "foreign_net": null, "support": 1060.0, "resistance": 1080.0, "take_profit_1": 1080.0, "take_profit_2": 1107.277754, "take_profit_3": 1319.34, "stop_loss": 1060.0, "risk_reward": 0.0, "rsi": 64.034672, "change_3m": 0.001726, "dividend_yield": 0.0287, "earnings_growth": 0.176, "rank": 33}]